weblint/__init__.py
weblint/_version.py
weblint-0.2.4.dist-info/METADATA
weblint-0.2.4.dist-info/WHEEL
weblint-0.2.4.dist-info/entry_points.txt
weblint-0.2.4.dist-info/top_level.txt
weblint-0.2.4.dist-info/RECORD
