Metadata-Version: 2.1
Name: weblint
Version: 0.2.4
Summary: UNKNOWN
Home-page: https://github.com/avengerpenguin/weblint
Author: Ross Fenning
Author-email: github@rossfenning.co.uk
License: UNKNOWN
Platform: UNKNOWN
Requires-Dist: scrapy
